matplotkit/__init__.py
matplotkit/annotations.py
matplotkit/colors.py
matplotkit/decorators.py
matplotkit/taylor.py
matplotkit-0.2.0.dist-info/METADATA
matplotkit-0.2.0.dist-info/WHEEL
matplotkit-0.2.0.dist-info/licenses/LICENSE
matplotkit-0.2.0.dist-info/RECORD
