Metadata-Version: 2.4
Name: matplotkit
Version: 0.2.0
Summary: A Python library for enhancing Matplotlib with additional features.
Author-email: SongshGeo <songshgeo@gmail.com>
License-File: LICENSE
Requires-Python: <4.0,>=3.8.1
Requires-Dist: matplotlib<4.0.0,>=3.0.0
Provides-Extra: dev
Requires-Dist: allure-pytest>=2.13.0; extra == 'dev'
Requires-Dist: flake8>=6.0.0; extra == 'dev'
Requires-Dist: ipykernel>=6.21.2; extra == 'dev'
Requires-Dist: isort>=5.12.0; extra == 'dev'
Requires-Dist: jupyterlab-execute-time>=2.3.1; extra == 'dev'
Requires-Dist: jupyterlab<5.0,>=4.0; extra == 'dev'
Requires-Dist: nbstripout>=0.6.1; extra == 'dev'
Requires-Dist: pre-commit-hooks>=4.4.0; extra == 'dev'
Requires-Dist: pydocstyle>=6.3.0; extra == 'dev'
Requires-Dist: pytest>=7.2.1; extra == 'dev'
Requires-Dist: snakeviz>=2.2.0; extra == 'dev'
Requires-Dist: tox-gh-actions>=3.2.0; extra == 'dev'
Requires-Dist: tox>=4.12.1; extra == 'dev'
